{
  "_fv": 24,
  "_type": "dimension",
  "definition": {
    "biomesInDimension": [
      {
        "value": "CUSTOM:Uhuuuuuuuuuu"
      }
    ],
    "worldGenType": "Normal world gen",
    "mainFillerBlock": {
      "value": "Blocks.FLOWING_WATER"
    },
    "fluidBlock": {
      "value": "Blocks.FLOWING_WATER"
    },
    "airColor": {
      "value": -10066330,
      "falpha": 0.0
    },
    "canRespawnHere": false,
    "hasFog": true,
    "isDark": true,
    "doesWaterVaporize": false,
    "sleepResult": "ALLOW",
    "hasSkyLight": false,
    "imitateOverworldBehaviour": true,
    "portalFrame": {
      "value": "Blocks.GOLD_BLOCK"
    },
    "portalParticles": {
      "value": "WATER_BUBBLE"
    },
    "portalLuminance": 0,
    "portalSound": {
      "value": "ambient.cave"
    },
    "igniterName": "Uhuuuuuuuuuuuuuuuuuuuu Portal Igniter",
    "igniterTab": {
      "value": "TOOLS"
    },
    "texture": "jwejk",
    "portalTexture": "zjsjfs",
    "enablePortal": true
  }
}